odoo8_addon_web_export_view-8.0.1.3.1-py2.7-nspkg.pth
odoo8_addon_web_export_view-8.0.1.3.1.dist-info/DESCRIPTION.rst
odoo8_addon_web_export_view-8.0.1.3.1.dist-info/METADATA
odoo8_addon_web_export_view-8.0.1.3.1.dist-info/RECORD
odoo8_addon_web_export_view-8.0.1.3.1.dist-info/WHEEL
odoo8_addon_web_export_view-8.0.1.3.1.dist-info/metadata.json
odoo8_addon_web_export_view-8.0.1.3.1.dist-info/namespace_packages.txt
odoo8_addon_web_export_view-8.0.1.3.1.dist-info/top_level.txt
odoo_addons/web_export_view/README.rst
odoo_addons/web_export_view/__init__.py
odoo_addons/web_export_view/__openerp__.py
odoo_addons/web_export_view/controllers/__init__.py
odoo_addons/web_export_view/controllers/controllers.py
odoo_addons/web_export_view/i18n/ar.po
odoo_addons/web_export_view/i18n/de.po
odoo_addons/web_export_view/i18n/es.po
odoo_addons/web_export_view/i18n/eu.po
odoo_addons/web_export_view/i18n/fi.po
odoo_addons/web_export_view/i18n/fr.po
odoo_addons/web_export_view/i18n/hr.po
odoo_addons/web_export_view/i18n/is.po
odoo_addons/web_export_view/i18n/it.po
odoo_addons/web_export_view/i18n/nl.po
odoo_addons/web_export_view/i18n/pt_BR.po
odoo_addons/web_export_view/i18n/pt_PT.po
odoo_addons/web_export_view/i18n/sl.po
odoo_addons/web_export_view/i18n/tr.po
odoo_addons/web_export_view/i18n/tr_TR.po
odoo_addons/web_export_view/i18n/web_export_view.pot
odoo_addons/web_export_view/static/description/icon.png
odoo_addons/web_export_view/static/src/js/web_export_view.js
odoo_addons/web_export_view/static/src/xml/web_export_view_template.xml
odoo_addons/web_export_view/view/web_export_view.xml
